ytfetch/__init__.py
ytfetch/cli.py
ytfetch/utils.py
ytfetch-1.1.5.dist-info/METADATA
ytfetch-1.1.5.dist-info/WHEEL
ytfetch-1.1.5.dist-info/entry_points.txt
ytfetch-1.1.5.dist-info/licenses/LICENSE
ytfetch-1.1.5.dist-info/RECORD
