Metadata-Version: 2.4
Name: ytfetch
Version: 1.1.5
Summary: A wrapper for yt-dlp with custom simple fetching flags
Project-URL: Homepage, https://github.com/voidsnax/ytFetch
Author: voidsnax
License: MIT
License-File: LICENSE
Keywords: converter,h264,mp3,playlist,youtubedownloader
Requires-Python: >=3.8
Requires-Dist: colorama
Requires-Dist: yt-dlp>=2025.12.08
